FIAT/P0.py
FIAT/Sminus.py
FIAT/SminusCurl.py
FIAT/SminusDiv.py
FIAT/__init__.py
FIAT/alfeld_sorokina.py
FIAT/argyris.py
FIAT/arnold_qin.py
FIAT/arnold_winther.py
FIAT/barycentric_interpolation.py
FIAT/bell.py
FIAT/bernardi_raugel.py
FIAT/bernstein.py
FIAT/brezzi_douglas_fortin_marini.py
FIAT/brezzi_douglas_marini.py
FIAT/brezzi_douglas_marini_cube.py
FIAT/bubble.py
FIAT/check_format_variant.py
FIAT/christiansen_hu.py
FIAT/crouzeix_raviart.py
FIAT/discontinuous.py
FIAT/discontinuous_lagrange.py
FIAT/discontinuous_pc.py
FIAT/discontinuous_raviart_thomas.py
FIAT/discontinuous_taylor.py
FIAT/dual_set.py
FIAT/enriched.py
FIAT/expansions.py
FIAT/fdm_element.py
FIAT/finite_element.py
FIAT/functional.py
FIAT/gauss_legendre.py
FIAT/gauss_lobatto_legendre.py
FIAT/gauss_radau.py
FIAT/gopalakrishnan_lederer_schoberl.py
FIAT/guzman_neilan.py
FIAT/hct.py
FIAT/hdiv_trace.py
FIAT/hdivcurl.py
FIAT/hellan_herrmann_johnson.py
FIAT/hermite.py
FIAT/hierarchical.py
FIAT/histopolation.py
FIAT/hu_zhang.py
FIAT/jacobi.py
FIAT/johnson_mercier.py
FIAT/kong_mulder_veldhuizen.py
FIAT/lagrange.py
FIAT/macro.py
FIAT/mardal_tai_winther.py
FIAT/mixed.py
FIAT/morley.py
FIAT/nedelec.py
FIAT/nedelec_second_kind.py
FIAT/nodal_enriched.py
FIAT/orientation_utils.py
FIAT/orthopoly.py
FIAT/pointwise_dual.py
FIAT/polynomial_set.py
FIAT/powell_sabin.py
FIAT/quadrature.py
FIAT/quadrature_element.py
FIAT/quadrature_schemes.py
FIAT/raviart_thomas.py
FIAT/reference_element.py
FIAT/regge.py
FIAT/restricted.py
FIAT/serendipity.py
FIAT/tensor_product.py
FIAT/xg_quad_data.py
finat/__init__.py
finat/alfeld_sorokina.py
finat/argyris.py
finat/arnold_qin.py
finat/aw.py
finat/bell.py
finat/bernardi_raugel.py
finat/cell_tools.py
finat/christiansen_hu.py
finat/citations.py
finat/cube.py
finat/direct_serendipity.py
finat/discontinuous.py
finat/element_factory.py
finat/enriched.py
finat/fiat_elements.py
finat/finiteelementbase.py
finat/guzman_neilan.py
finat/hct.py
finat/hdivcurl.py
finat/hermite.py
finat/hz.py
firedrake_fiat-2025.10.0.dist-info/licenses/AUTHORS
firedrake_fiat-2025.10.0.dist-info/licenses/COPYING
firedrake_fiat-2025.10.0.dist-info/licenses/COPYING.LESSER
firedrake_fiat-2025.10.0.dist-info/METADATA
firedrake_fiat-2025.10.0.dist-info/WHEEL
firedrake_fiat-2025.10.0.dist-info/top_level.txt
firedrake_fiat-2025.10.0.dist-info/RECORD
