Metadata-Version: 2.4
Name: firedrake-fiat
Version: 2025.10.0
Summary: FInite element Automatic Tabulator
Author-email: "Robert C. Kirby et al." <fenics-dev@googlegroups.com>, Imperial College London and others <david.ham@imperial.ac.uk>
Project-URL: Repository, https://github.com/firedrakeproject/fiat.git
Classifier: Programming Language :: Python
Requires-Python: >=3.10
License-File: COPYING
License-File: COPYING.LESSER
License-File: AUTHORS
Requires-Dist: fenics-ufl>=2025.2.0
Requires-Dist: numpy>=1.16
Requires-Dist: recursivenodes
Requires-Dist: scipy
Requires-Dist: symengine
Requires-Dist: sympy
Provides-Extra: doc
Requires-Dist: setuptools; extra == "doc"
Requires-Dist: sphinx; extra == "doc"
Provides-Extra: test
Requires-Dist: pytest; extra == "test"
Dynamic: license-file
